{
  "kind": "singleType",
  "collectionName": "finances",
  "info": {
    "singularName": "finance",
    "pluralName": "finances",
    "displayName": "finance",
    "description": ""
  },
  "options": {
    "draftAndPublish": true
  },
  "pluginOptions": {},
  "attributes": {
    "totalAmountLoanedOut": {
      "type": "decimal"
    },
    "totalAmountPaid": {
      "type": "decimal"
    },
    "netProfitLoss": {
      "type": "decimal"
    },
    "totalAmountUnpaid": {
      "type": "decimal"
    },
    "totalAmountInvestedIn": {
      "type": "decimal"
    },
    "TotalInvestedInterestMade": {
      "type": "decimal"
    }
  }
}
